nse_reports/__init__.py
nse_reports/combineoi.py
nse_reports/downloader.py
nse_reports-1.0.4.dist-info/METADATA
nse_reports-1.0.4.dist-info/WHEEL
nse_reports-1.0.4.dist-info/top_level.txt
nse_reports-1.0.4.dist-info/RECORD
