Metadata-Version: 2.4
Name: nse_reports
Version: 1.0.4
Summary: A library to download NSE FO Bhavcopy reports
Author: Alok Kumar Yadav
Classifier: Programming Language :: Python :: 3
Classifier: License :: OSI Approved :: MIT License
Classifier: Operating System :: OS Independent
Requires-Python: >=3.6
Requires-Dist: requests
Dynamic: author
Dynamic: classifier
Dynamic: requires-dist
Dynamic: requires-python
Dynamic: summary
